artello/__init__.py
artello/data.py
artello/inference.py
artello/models.py
artello/training.py
artello-0.1.0.dist-info/LICENSE
artello-0.1.0.dist-info/METADATA
artello-0.1.0.dist-info/WHEEL
artello-0.1.0.dist-info/top_level.txt
artello-0.1.0.dist-info/RECORD
